MANIFEST.in
README.rst
setup.cfg
setup.py
os_benchmark/__init__.py
os_benchmark/benchmarks.py
os_benchmark/console.py
os_benchmark/errors.py
os_benchmark/utils.py
os_benchmark.egg-info/PKG-INFO
os_benchmark.egg-info/SOURCES.txt
os_benchmark.egg-info/dependency_links.txt
os_benchmark.egg-info/entry_points.txt
os_benchmark.egg-info/not-zip-safe
os_benchmark.egg-info/requires.txt
os_benchmark.egg-info/top_level.txt
os_benchmark/drivers/__init__.py
os_benchmark/drivers/alibaba.py
os_benchmark/drivers/aws.py
os_benchmark/drivers/azure.py
os_benchmark/drivers/backblaze.py
os_benchmark/drivers/backblaze_s3.py
os_benchmark/drivers/base.py
os_benchmark/drivers/bluvalt.py
os_benchmark/drivers/bso.py
os_benchmark/drivers/dell_ecs_test.py
os_benchmark/drivers/digitalocean.py
os_benchmark/drivers/errors.py
os_benchmark/drivers/exoscale.py
os_benchmark/drivers/fs.py
os_benchmark/drivers/google.py
os_benchmark/drivers/hopla.py
os_benchmark/drivers/hopla_s3.py
os_benchmark/drivers/ibm.py
os_benchmark/drivers/ionos.py
os_benchmark/drivers/linode.py
os_benchmark/drivers/obs.py
os_benchmark/drivers/oracle.py
os_benchmark/drivers/oracle_s3.py
os_benchmark/drivers/otc.py
os_benchmark/drivers/outscale.py
os_benchmark/drivers/ovhcloud.py
os_benchmark/drivers/ram.py
os_benchmark/drivers/s3.py
os_benchmark/drivers/scaleway.py
os_benchmark/drivers/swift.py
os_benchmark/drivers/upcloud.py
os_benchmark/drivers/utils.py
os_benchmark/drivers/wasabi.py
os_benchmark/tests/__init__.py
os_benchmark/tests/test_utils.py