Metadata-Version: 2.1
Name: os-benchmark
Version: 0.7.4
Summary: Handy tool for Object Storage performance benchmark
Home-page: https://github.com/cloudmercato/os-benchmark
Author: Anthony Monthe
Author-email: anthony@cloud-mercato.com
License: BSD 3-Clause License
Keywords: benchmark,cloud,object storage
Platform: UNKNOWN
Classifier: Development Status :: 4 - Beta
Classifier: Environment :: Console
Classifier: Intended Audience :: Developers
Classifier: Intended Audience :: System Administrators
Classifier: Intended Audience :: Telecommunications Industry
Classifier: License :: OSI Approved :: BSD License
Classifier: Operating System :: OS Independent
Classifier: Programming Language :: Python
Classifier: Programming Language :: Python :: 3
Classifier: Topic :: Internet :: File Transfer Protocol (FTP)
Classifier: Topic :: Internet :: WWW/HTTP
Classifier: Topic :: System :: Networking
Classifier: Topic :: System :: Benchmark
Provides-Extra: s3
Provides-Extra: swift
Provides-Extra: exoscale
Provides-Extra: azure
Provides-Extra: bluvalt
Provides-Extra: digitalocean
Provides-Extra: linode
Provides-Extra: backblaze_s3
Provides-Extra: bso
Provides-Extra: google_s3
Provides-Extra: otc
Provides-Extra: obs
Provides-Extra: scaleway
Provides-Extra: wasabi
Provides-Extra: oracle
Provides-Extra: oracle_s3
Provides-Extra: google
Provides-Extra: ibm
Provides-Extra: ovhcloud
